LICENSE
README.md
setup.cfg
setup.py
ampscz_lochness.egg-info/PKG-INFO
ampscz_lochness.egg-info/SOURCES.txt
ampscz_lochness.egg-info/dependency_links.txt
ampscz_lochness.egg-info/requires.txt
ampscz_lochness.egg-info/top_level.txt
lochness/__init__.py
lochness/__version__.py
lochness/beiwe/__init__.py
lochness/box/__init__.py
lochness/config/__init__.py
lochness/daemon/__init__.py
lochness/daris/__init__.py
lochness/dropbox/__init__.py
lochness/dropbox/baker.py
lochness/dropbox/cbsn.py
lochness/dropbox/hash.py
lochness/dropbox/mclean.py
lochness/dropbox/multisense.py
lochness/dropbox/nrg.py
lochness/email/__init__.py
lochness/functools/__init__.py
lochness/hdd/__init__.py
lochness/hdd/buckner.py
lochness/hdd/coombs.py
lochness/icognition/__init__.py
lochness/keyring/__init__.py
lochness/mediaflux/__init__.py
lochness/mindlamp/__init__.py
lochness/net/__init__.py
lochness/onlinescoring/__init__.py
lochness/redcap/__init__.py
lochness/redcap/data_trigger_capture.py
lochness/redcap/process_piis.py
lochness/rpms/__init__.py
lochness/scheduler/__init__.py
lochness/ssh/__init__.py
lochness/transfer/__init__.py
lochness/tree/__init__.py
lochness/xnat/__init__.py
scripts/listen_to_redcap.py
scripts/lochness_check_config.py
scripts/lochness_create_template.py
scripts/phoenix_generator.py
scripts/sync.py