Metadata-Version: 2.1
Name: ampscz-lochness
Version: 0.1.6
Summary: Data aggregator
Home-page: https://github.com/AMP-SCZ/lochness
Download-URL: https://github.com/AMP-SCZ/lochness/archive/refs/tags/v0.1.6.zip
Author: DPACC
Author-email: kevincho@bwh.harvard.edu
License: UNKNOWN
Keywords: data,dataflow,download,datalake,U24
Platform: UNKNOWN
Classifier: Programming Language :: Python :: 3
Classifier: License :: OSI Approved :: MIT License
Requires-Python: >=3.7
License-File: LICENSE
